generative_content_pipeline/__init__.py
generative_content_pipeline/hello.py
generative_content_pipeline-0.1.3.dist-info/METADATA
generative_content_pipeline-0.1.3.dist-info/WHEEL
generative_content_pipeline-0.1.3.dist-info/top_level.txt
generative_content_pipeline-0.1.3.dist-info/RECORD
