Metadata-Version: 2.4
Name: generative-content-pipeline
Version: 0.1.3
Summary: Add your description here
Requires-Python: >=3.12
Requires-Dist: npx>=0.1.6
Requires-Dist: prettier>=0.0.7
